<annotation>
	<folder>Mary_WorkingImages</folder>
	<filename>DC20_3387_TarSpot_6photo_1_2020-08-27-01-23-27.jpg_01_02.jpg</filename>
	<path>/Volumes/ThompsonLab/Personnel/Elyse/Student_Folders/Mary_WorkingImages/DC20_3387_TarSpot_6photo_1_2020-08-27-01-23-27.jpg_01_02.jpg</path>
	<source>
		<database>Unknown</database>
	</source>
	<size>
		<width>360</width>
		<height>213</height>
		<depth>3</depth>
	</size>
	<segmented>0</segmented>
	<object>
		<name>tarspot</name>
		<pose>Unspecified</pose>
		<truncated>0</truncated>
		<difficult>0</difficult>
		<bndbox>
			<xmin>46</xmin>
			<ymin>92</ymin>
			<xmax>53</xmax>
			<ymax>100</ymax>
		</bndbox>
	</object>
	<object>
		<name>tarspot</name>
		<pose>Unspecified</pose>
		<truncated>0</truncated>
		<difficult>0</difficult>
		<bndbox>
			<xmin>65</xmin>
			<ymin>127</ymin>
			<xmax>72</xmax>
			<ymax>133</ymax>
		</bndbox>
	</object>
	<object>
		<name>tarspot</name>
		<pose>Unspecified</pose>
		<truncated>0</truncated>
		<difficult>0</difficult>
		<bndbox>
			<xmin>41</xmin>
			<ymin>182</ymin>
			<xmax>47</xmax>
			<ymax>190</ymax>
		</bndbox>
	</object>
	<object>
		<name>tarspot</name>
		<pose>Unspecified</pose>
		<truncated>0</truncated>
		<difficult>0</difficult>
		<bndbox>
			<xmin>190</xmin>
			<ymin>124</ymin>
			<xmax>197</xmax>
			<ymax>133</ymax>
		</bndbox>
	</object>
	<object>
		<name>tarspot</name>
		<pose>Unspecified</pose>
		<truncated>0</truncated>
		<difficult>0</difficult>
		<bndbox>
			<xmin>276</xmin>
			<ymin>85</ymin>
			<xmax>284</xmax>
			<ymax>93</ymax>
		</bndbox>
	</object>
</annotation>
