<annotation>
	<folder>Emily_WorkingImages</folder>
	<filename>DC20_2241_TarSpot_6photo_1_2020-08-27-09-51-55.jpg_02_02.jpg</filename>
	<path>Z:\Personnel\Elyse\Student_Folders\Emily_WorkingImages\DC20_2241_TarSpot_6photo_1_2020-08-27-09-51-55.jpg_02_02.jpg</path>
	<source>
		<database>Unknown</database>
	</source>
	<size>
		<width>360</width>
		<height>213</height>
		<depth>3</depth>
	</size>
	<segmented>0</segmented>
	<object>
		<name>tarspot</name>
		<pose>Unspecified</pose>
		<truncated>0</truncated>
		<difficult>0</difficult>
		<bndbox>
			<xmin>95</xmin>
			<ymin>168</ymin>
			<xmax>107</xmax>
			<ymax>182</ymax>
		</bndbox>
	</object>
	<object>
		<name>tarspot</name>
		<pose>Unspecified</pose>
		<truncated>0</truncated>
		<difficult>0</difficult>
		<bndbox>
			<xmin>104</xmin>
			<ymin>92</ymin>
			<xmax>114</xmax>
			<ymax>106</ymax>
		</bndbox>
	</object>
	<object>
		<name>tarspot</name>
		<pose>Unspecified</pose>
		<truncated>0</truncated>
		<difficult>0</difficult>
		<bndbox>
			<xmin>201</xmin>
			<ymin>83</ymin>
			<xmax>211</xmax>
			<ymax>97</ymax>
		</bndbox>
	</object>
	<object>
		<name>tarspot</name>
		<pose>Unspecified</pose>
		<truncated>0</truncated>
		<difficult>0</difficult>
		<bndbox>
			<xmin>148</xmin>
			<ymin>149</ymin>
			<xmax>157</xmax>
			<ymax>157</ymax>
		</bndbox>
	</object>
	<object>
		<name>tarspot</name>
		<pose>Unspecified</pose>
		<truncated>0</truncated>
		<difficult>0</difficult>
		<bndbox>
			<xmin>269</xmin>
			<ymin>184</ymin>
			<xmax>288</xmax>
			<ymax>211</ymax>
		</bndbox>
	</object>
	<object>
		<name>tarspot</name>
		<pose>Unspecified</pose>
		<truncated>0</truncated>
		<difficult>0</difficult>
		<bndbox>
			<xmin>208</xmin>
			<ymin>71</ymin>
			<xmax>221</xmax>
			<ymax>88</ymax>
		</bndbox>
	</object>
	<object>
		<name>tarspot</name>
		<pose>Unspecified</pose>
		<truncated>0</truncated>
		<difficult>0</difficult>
		<bndbox>
			<xmin>310</xmin>
			<ymin>23</ymin>
			<xmax>320</xmax>
			<ymax>32</ymax>
		</bndbox>
	</object>
	<object>
		<name>tarspot</name>
		<pose>Unspecified</pose>
		<truncated>1</truncated>
		<difficult>0</difficult>
		<bndbox>
			<xmin>315</xmin>
			<ymin>1</ymin>
			<xmax>327</xmax>
			<ymax>9</ymax>
		</bndbox>
	</object>
</annotation>
